odoo/addons/tms_product/README.rst
odoo/addons/tms_product/__init__.py
odoo/addons/tms_product/__manifest__.py
odoo/addons/tms_product/i18n/tms_product.pot
odoo/addons/tms_product/models/__init__.py
odoo/addons/tms_product/models/fleet_vehicle.py
odoo/addons/tms_product/models/product_template.py
odoo/addons/tms_product/models/stock_lot.py
odoo/addons/tms_product/models/stock_move.py
odoo/addons/tms_product/models/stock_picking.py
odoo/addons/tms_product/models/transportable_product.py
odoo/addons/tms_product/readme/CONTRIBUTORS.md
odoo/addons/tms_product/readme/CREDITS.md
odoo/addons/tms_product/readme/DESCRIPTION.md
odoo/addons/tms_product/readme/MAINTAINERS.md
odoo/addons/tms_product/readme/USAGE.md
odoo/addons/tms_product/security/ir.model.access.csv
odoo/addons/tms_product/static/description/icon.png
odoo/addons/tms_product/static/description/icon.svg
odoo/addons/tms_product/static/description/index.html
odoo/addons/tms_product/views/fleet_vehicle_views.xml
odoo/addons/tms_product/views/product_template_views.xml
odoo/addons/tms_product/views/stock_lot_views.xml
odoo/addons/tms_product/views/stock_picking_views.xml
odoo/addons/tms_product/views/transportable_product_views.xml
odoo_addon_tms_product-17.0.1.0.0.2.dist-info/METADATA
odoo_addon_tms_product-17.0.1.0.0.2.dist-info/WHEEL
odoo_addon_tms_product-17.0.1.0.0.2.dist-info/top_level.txt
odoo_addon_tms_product-17.0.1.0.0.2.dist-info/RECORD
